LICENSE
README.md
setup.py
upbit/__init__.py
upbit/api.py
upbit/client.py
upbit/market.py
upbit/short.py
upbit/websocket.py
upbit.py.egg-info/PKG-INFO
upbit.py.egg-info/SOURCES.txt
upbit.py.egg-info/dependency_links.txt
upbit.py.egg-info/requires.txt
upbit.py.egg-info/top_level.txt