Metadata-Version: 2.1
Name: upbit.py
Version: 1.0.3
Summary: Upbit API
Home-page: https://github.com/Beta5051/upbit.py
Author-email: beta5051@gmail.com
License: MIT
Platform: UNKNOWN
